{"FAUST":[{"ClueText":"Goethe's soul-seller","ClueSource":2}],"FIDO":[{"ClueText":"Classic dog name","ClueSource":2}],"AKIN":[{"ClueText":"Analogous","ClueSource":2}],"UNPC":[{"ClueText":"Like sexist jokes, briefly","ClueSource":2}],"SOLEMN":[{"ClueText":"Very serious","ClueSource":2}],"TWO":[{"ClueText":"Dos, in English","ClueSource":2}],"DIAL":[{"ClueText":"Volume knob, e.g.","ClueSource":2}],"DRAT":[{"ClueText":"\"Darn!\"","ClueSource":2}],"IOTA":[{"ClueText":"I, to Icarus","ClueSource":2}],"AVIS":[{"ClueText":"Budget competitor","ClueSource":2}],"LECTERN":[{"ClueText":"Speaker's stand","ClueSource":2}],"EACH":[{"ClueText":"Apiece","ClueSource":2}],"EMO":[{"ClueText":"Mood music?","ClueSource":2}],"AERIALYOGA":[{"ClueText":"Exercise regimen involving a hammock","ClueSource":2}],"CSPAN":[{"ClueText":"Senate hearing airer","ClueSource":2}],"HASNT":[{"ClueText":"___ a clue (is lost)","ClueSource":2}],"IKNOW":[{"ClueText":"\"You already told me\"","ClueSource":2}],"ROVE":[{"ClueText":"Wander","ClueSource":2}],"MESA":[{"ClueText":"Flat-topped hill","ClueSource":2}],"DIPLOMATICCORPS":[{"ClueText":"*Ambassador's group (note every starred answer's initials!)","ClueSource":2}],"MACAO":[{"ClueText":"Asian gambling center","ClueSource":2}],"CERA":[{"ClueText":"Michael of \"Molly's Game\"","ClueSource":2}],"ONCE":[{"ClueText":"Fairy tale opener","ClueSource":2}],"ATASTE":[{"ClueText":"One small bite","ClueSource":2}],"IAN":[{"ClueText":"\"At Seventeen\" singer Janis","ClueSource":2}],"MIC":[{"ClueText":"Open ___ night","ClueSource":2}],"ITCH":[{"ClueText":"Back scratcher target","ClueSource":2}],"ERRANT":[{"ClueText":"Off the mark","ClueSource":2}],"RICO":[{"ClueText":"Puerto ___","ClueSource":2}],"MOUNTAINTRAIL":[{"ClueText":"*Path on steep terrain","ClueSource":2}],"MUFF":[{"ClueText":"Bungle","ClueSource":2}],"OREO":[{"ClueText":"Cookie in some sundaes","ClueSource":2}],"ULTIMATUMS":[{"ClueText":"Final demands","ClueSource":2}],"IMAGO":[{"ClueText":"Adult insect","ClueSource":2}],"NEPAL":[{"ClueText":"Kathmandu's country","ClueSource":2}],"TORSI":[{"ClueText":"They have rock-hard abs","ClueSource":2}],"URL":[{"ClueText":"Web address, for short","ClueSource":2}],"COMEON":[{"ClueText":"Marketing lure","ClueSource":2}],"CYAN":[{"ClueText":"Blue-green hue","ClueSource":2}],"ALOT":[{"ClueText":"\"Thanks ___!\"","ClueSource":2}],"NATE":[{"ClueText":"\"Great\" kid-lit detective","ClueSource":2}],"FETCH":[{"ClueText":"Dog park game","ClueSource":2}],"CLAP":[{"ClueText":"Applaud","ClueSource":2}],"APR":[{"ClueText":"First 30-day mo.","ClueSource":2}],"MOOLA":[{"ClueText":"$$$","ClueSource":2}],"MISO":[{"ClueText":"Japanese soup","ClueSource":2}],"FOIL":[{"ClueText":"Aluminum wrap","ClueSource":2}],"AGASSI":[{"ClueText":"U.S. Open champ Andre","ClueSource":2}],"ANTHEMS":[{"ClueText":"Country music?","ClueSource":2}],"SAYNO":[{"ClueText":"Decline a request","ClueSource":2}],"GOT":[{"ClueText":"Understood","ClueSource":2}],"MAGNOLIASTATE":[{"ClueText":"*Nickname of Biloxi's home","ClueSource":2}],"GOSH":[{"ClueText":"\"Gee willikers!\"","ClueSource":2}],"TUCKER":[{"ClueText":"Tanya who sang \"Delta Dawn\"","ClueSource":2}],"TEAPOT":[{"ClueText":"66-Across vessel","ClueSource":2}],"TASER":[{"ClueText":"Electric dart shooter","ClueSource":2}],"ECOLI":[{"ClueText":"Raw meat danger","ClueSource":2}],"YOU":[{"ClueText":"\"Girls Like ___\" (2018 hit)","ClueSource":2}],"ACT":[{"ClueText":"Behave","ClueSource":2}],"SHOOIN":[{"ClueText":"Sure winner","ClueSource":2}],"ORAL":[{"ClueText":"Face-to-face exam","ClueSource":2}],"ONTO":[{"ClueText":"Burst ___ the scene","ClueSource":2}],"ICET":[{"ClueText":"\"Rhyme Pays\" rapper","ClueSource":2}],"CHIA":[{"ClueText":"Pet name?","ClueSource":2}],"HIKE":[{"ClueText":"Nature walk","ClueSource":2}],"INON":[{"ClueText":"Aware of","ClueSource":2}],"AGED":[{"ClueText":"Elderly","ClueSource":2}],"SOUTHERNCOOKING":[{"ClueText":"*Shrimp and grits, etc.","ClueSource":2}],"TOE":[{"ClueText":"Boot tip","ClueSource":2}],"OPT":[{"ClueText":"Choose","ClueSource":2}],"ELMO":[{"ClueText":"\"Blondie\" boy","ClueSource":2}],"MATE":[{"ClueText":"Ram, for a ewe","ClueSource":2}],"PEKOE":[{"ClueText":"Oolong alternative","ClueSource":2}],"RISE":[{"ClueText":"Get out of bed","ClueSource":2}],"SLOT":[{"ClueText":"Coin opening","ClueSource":2}],"TREND":[{"ClueText":"Popular Twitter topic","ClueSource":2}]}