{"ICEDAM":[{"ClueText":"*Aftermath of a white Christmas eave?","ClueSource":2}],"IHOP":[{"ClueText":"Breakfast chain that temporarily flipped its \"p\" to a \"b\"","ClueSource":2}],"CAMEAPART":[{"ClueText":"Broke into pieces","ClueSource":2}],"EVENMONEY":[{"ClueText":"50-50 bet","ClueSource":2}],"DARNIT":[{"ClueText":"\"Rats!\"","ClueSource":2}],"ANTE":[{"ClueText":"Pot starter","ClueSource":2}],"MAA":[{"ClueText":"Goat's call","ClueSource":2}],"SIL":[{"ClueText":"Part of RSVP","ClueSource":2}],"STARR":[{"ClueText":"Beatles' beat guy","ClueSource":2}],"ISRAEL":[{"ClueText":"Haifa's country","ClueSource":2}],"LAMBDA":[{"ClueText":"Letter between kappa and mu","ClueSource":2}],"COUP":[{"ClueText":"Power grab","ClueSource":2}],"CARAMELS":[{"ClueText":"Chewy candies","ClueSource":2}],"OSAKA":[{"ClueText":"Tennis star Naomi","ClueSource":2}],"UNPEG":[{"ClueText":"Let float, as a currency","ClueSource":2}],"POSSE":[{"ClueText":"Crew","ClueSource":2}],"HAVANA":[{"ClueText":"Cuban capital","ClueSource":2}],"TSA":[{"ClueText":"Org. with a PreCheck program","ClueSource":2}],"ASNO":[{"ClueText":"\"It comes ___ surprise\"","ClueSource":2}],"OMERTA":[{"ClueText":"Mafia code of silence","ClueSource":2}],"ARM":[{"ClueText":"Pitcher's asset","ClueSource":2}],"RAPS":[{"ClueText":"Emulates Eminem","ClueSource":2}],"PENNE":[{"ClueText":"\"Alla vodka\" pasta","ClueSource":2}],"CRABCAKES":[{"ClueText":"Signature Maryland appetizers","ClueSource":2}],"CITED":[{"ClueText":"Included in a bibliography","ClueSource":2}],"CADENZA":[{"ClueText":"Concerto solo passage","ClueSource":2}],"AMI":[{"ClueText":"Bon ___ (cleaner brand)","ClueSource":2}],"FIREDAMAGE":[{"ClueText":"*Insurance might cover it","ClueSource":2}],"FINE":[{"ClueText":"\"Be that way!\"","ClueSource":2}],"SPOTLIT":[{"ClueText":"Singled out on stage","ClueSource":2}],"SICS":[{"ClueText":"Commands to attack","ClueSource":2}],"LATERON":[{"ClueText":"Storyteller's \"fast forward\"","ClueSource":2}],"LADE":[{"ClueText":"Put on board","ClueSource":2}],"IAN":[{"ClueText":"McKellen who portrayed Gandalf","ClueSource":2}],"ANEW":[{"ClueText":"Over again","ClueSource":2}],"WAR":[{"ClueText":"___ of attrition","ClueSource":2}],"ELISE":[{"ClueText":"Beethoven dedicatee","ClueSource":2}],"ITSERVICE":[{"ClueText":"PC support","ClueSource":2}],"SEPARATES":[{"ClueText":"Splits up","ClueSource":2}],"ERAS":[{"ClueText":"Notable times","ClueSource":2}],"CREATEDAMONSTER":[{"ClueText":"*Made something with unexpected consequences","ClueSource":2}],"ANIMATOR":[{"ClueText":"Hanna or Barbera","ClueSource":2}],"MAAMS":[{"ClueText":"Polite addresses","ClueSource":2}],"OZZY":[{"ClueText":"Black Sabbath's Osbourne","ClueSource":2}],"STYNE":[{"ClueText":"Composer Jule","ClueSource":2}],"RAZZ":[{"ClueText":"Try to annoy","ClueSource":2}],"SPA":[{"ClueText":"Place for a \"me day\"","ClueSource":2}],"IRKS":[{"ClueText":"Succeeds in annoying","ClueSource":2}],"KVETCH":[{"ClueText":"Gripe","ClueSource":2}],"SERENE":[{"ClueText":"Very calm","ClueSource":2}],"AZALEAS":[{"ClueText":"Springtime bloomers","ClueSource":2}],"LEANNE":[{"ClueText":"HGTV designer Ford","ClueSource":2}],"WHOMOVEDMY":[{"ClueText":"With 63-Across, business fable with two mice ... or a hint to a word hidden in each starred answer","ClueSource":2}],"WHEAT":[{"ClueText":"Cream of ___","ClueSource":2}],"HARMS":[{"ClueText":"Injures","ClueSource":2}],"OBAMA":[{"ClueText":"Michelle who wrote \"Becoming\"","ClueSource":2}],"DONNE":[{"ClueText":"\"A Valediction: Forbidding Mourning\" poet","ClueSource":2}],"ERR":[{"ClueText":"Mess up","ClueSource":2}],"HABANEROS":[{"ClueText":"Jalapenos' spicier cousins","ClueSource":2}],"NAVAL":[{"ClueText":"Like a sea battle","ClueSource":2}],"NOAH":[{"ClueText":"Animal pair rescuer","ClueSource":2}],"LORE":[{"ClueText":"Often-repeated tales","ClueSource":2}],"ERAT":[{"ClueText":"Part of QED","ClueSource":2}],"TEN":[{"ClueText":"Jack's value in blackjack","ClueSource":2}],"BONITO":[{"ClueText":"Tuna relative","ClueSource":2}],"BCC":[{"ClueText":"Stealthy email letters","ClueSource":2}],"AMMO":[{"ClueText":"BBs and such","ClueSource":2}],"CNN":[{"ClueText":"Anderson Cooper's channel","ClueSource":2}],"CANCER":[{"ClueText":"Tropic of ___","ClueSource":2}],"TSAR":[{"ClueText":"Old Russian monarch","ClueSource":2}],"HEE":[{"ClueText":"Half a laugh","ClueSource":2}],"CHEESE":[{"ClueText":"See 47-Across","ClueSource":2}]}