{"HAM":[{"ClueText":"\"Green Eggs and ___ \"","ClueSource":2}],"HINDU":[{"ClueText":"Gandhi, religiously","ClueSource":2}],"ACORN":[{"ClueText":"Oak's beginning","ClueSource":2}],"MYBAD":[{"ClueText":"\"Whoops!\"","ClueSource":2}],"CASSIS":[{"ClueText":"Black currant liqueur","ClueSource":2}],"CAMEROON":[{"ClueText":"Its capital is Yaounde","ClueSource":2}],"ANO":[{"ClueText":"Rioja bottle datum","ClueSource":2}],"SYN":[{"ClueText":"Antonym's opposite: Abbr.","ClueSource":2}],"SOS":[{"ClueText":"... --- ..., in Morse code","ClueSource":2}],"INTOW":[{"ClueText":"Following behind","ClueSource":2}],"SEENIT":[{"ClueText":"Movie suggestion veto","ClueSource":2}],"DISH":[{"ClueText":"Any entree","ClueSource":2}],"DAMSELS":[{"ClueText":"Dated women?","ClueSource":2}],"IRAS":[{"ClueText":"Popular tax shelters, for short","ClueSource":2}],"SISI":[{"ClueText":"\"Sure thing, Joaquin!\"","ClueSource":2}],"HAHS":[{"ClueText":"Derisive cries","ClueSource":2}],"ICY":[{"ClueText":"Cold and slippery","ClueSource":2}],"ANYONE":[{"ClueText":"Nobody in particular","ClueSource":2}],"ARIA":[{"ClueText":"La Scala highlight","ClueSource":2}],"NOB":[{"ClueText":"San Francisco's ___ Hill","ClueSource":2}],"MONSTERMASH":[{"ClueText":"TV reboot about treating zombie apocalypse victims?","ClueSource":2}],"RARE":[{"ClueText":"Like some coins and stamps","ClueSource":2}],"DRAPE":[{"ClueText":"Hang loosely","ClueSource":2}],"PECK":[{"ClueText":"Not just air-kiss","ClueSource":2}],"ONASSIS":[{"ClueText":"Kennedy children's stepfather","ClueSource":2}],"UNDERTHEWIRE":[{"ClueText":"... about Baltimore sewers?","ClueSource":2}],"TONO":[{"ClueText":"___ avail","ClueSource":2}],"HEATS":[{"ClueText":"Warms","ClueSource":2}],"EDIFIED":[{"ClueText":"Enlightened","ClueSource":2}],"COOED":[{"ClueText":"Spoke like a lover","ClueSource":2}],"TELLER":[{"ClueText":"The \"T\" in ATM","ClueSource":2}],"LASH":[{"ClueText":"Batted hair, informally","ClueSource":2}],"ETRE":[{"ClueText":"To exist, to Sartre","ClueSource":2}],"REIN":[{"ClueText":"Guiding strap","ClueSource":2}],"WALKONAIR":[{"ClueText":"Feel euphoric","ClueSource":2}],"WHOM":[{"ClueText":"To ___ it may concern","ClueSource":2}],"AUDI":[{"ClueText":"German car brand","ClueSource":2}],"LEON":[{"ClueText":"\"Trinity\" author Uris","ClueSource":2}],"RANDI":[{"ClueText":"Paranormal skeptic James","ClueSource":2}],"SATE":[{"ClueText":"Fill completely","ClueSource":2}],"HUE":[{"ClueText":"Tint","ClueSource":2}],"NOTFAIR":[{"ClueText":"Like life, some say","ClueSource":2}],"ICUS":[{"ClueText":"Post-op places","ClueSource":2}],"RECESSES":[{"ClueText":"Congressional breaks","ClueSource":2}],"SRI":[{"ClueText":"Lanka lead-in","ClueSource":2}],"ODOR":[{"ClueText":"___-Eaters","ClueSource":2}],"RIPINTO":[{"ClueText":"Start tearing","ClueSource":2}],"SINCEWHEN":[{"ClueText":"Question of indignant surprise","ClueSource":2}],"WELT":[{"ClueText":"Paintball mark","ClueSource":2}],"MINIME":[{"ClueText":"Dr. Evil's little clone","ClueSource":2}],"MARX":[{"ClueText":"\"Das Kapital\" author","ClueSource":2}],"ERECTS":[{"ClueText":"Constructs","ClueSource":2}],"EDUCE":[{"ClueText":"Bring out","ClueSource":2}],"PARADISELOST":[{"ClueText":"... about plane crash survivors in heaven?","ClueSource":2}],"ASHEN":[{"ClueText":"Wan","ClueSource":2}],"ORCAS":[{"ClueText":"SeaWorld stopped breeding them","ClueSource":2}],"SAUCE":[{"ClueText":"Alfredo or marinara","ClueSource":2}],"TYPEA":[{"ClueText":"Go-getter sort","ClueSource":2}],"ADMIRES":[{"ClueText":"Respects","ClueSource":2}],"ABBI":[{"ClueText":"Jacobson of \"Broad City\"","ClueSource":2}],"DRUM":[{"ClueText":"Tom-tom, e.g.","ClueSource":2}],"MOTH":[{"ClueText":"Insect drawn to light","ClueSource":2}],"STRAY":[{"ClueText":"Pound inhabitant","ClueSource":2}],"BRONXCHEERS":[{"ClueText":"... about drinking with friends in an NYC borough?","ClueSource":2}],"ECO":[{"ClueText":"\"System\" prefix","ClueSource":2}],"EAR":[{"ClueText":"Corn unit","ClueSource":2}],"RTE":[{"ClueText":"Waze way, briefly","ClueSource":2}],"CUP":[{"ClueText":"Trophy shape","ClueSource":2}],"BUTT":[{"ClueText":"___ heads (clash)","ClueSource":2}],"TECATE":[{"ClueText":"Corona competitor","ClueSource":2}],"ACE":[{"ClueText":"Point of no return?","ClueSource":2}],"IMHO":[{"ClueText":"Texter's \"Just sayin'\"","ClueSource":2}],"SNORES":[{"ClueText":"Noisy z's","ClueSource":2}],"SEA":[{"ClueText":"Neptune's domain","ClueSource":2}]}