{"ISLE":[{"ClueText":"Castaway's home, perhaps","ClueSource":2}],"ICBM":[{"ClueText":"Long-range weapon, for short","ClueSource":2}],"SORE":[{"ClueText":"Achy","ClueSource":2}],"LAIR":[{"ClueText":"Dragon's home","ClueSource":2}],"EXOCRINE":[{"ClueText":"Like some glands","ClueSource":2}],"SAMBA":[{"ClueText":"Brazilian dance","ClueSource":2}],"SALAMI":[{"ClueText":"Italian sausage","ClueSource":2}],"ADIN":[{"ClueText":"Score after deuce, at times","ClueSource":2}],"MITT":[{"ClueText":"Baseball glove","ClueSource":2}],"BEEB":[{"ClueText":"English channel's nickname, with \"the\"","ClueSource":2}],"AURA":[{"ClueText":"Spiritual emanation","ClueSource":2}],"CPA":[{"ClueText":"Balancing pro?","ClueSource":2}],"CONSENTSTO":[{"ClueText":"Gives permission for","ClueSource":2}],"PIT":[{"ClueText":"Barbecue site","ClueSource":2}],"ADO":[{"ClueText":"Big fuss","ClueSource":2}],"COAX":[{"ClueText":"Cajole","ClueSource":2}],"ADIEU":[{"ClueText":"Farewell, in French","ClueSource":2}],"VOID":[{"ClueText":"___ where prohibited","ClueSource":2}],"VIKKI":[{"ClueText":"\"It Must Be Him\" singer Carr","ClueSource":2}],"BRIO":[{"ClueText":"Get-up-and-go","ClueSource":2}],"LITER":[{"ClueText":"Sprite bottle size","ClueSource":2}],"INTO":[{"ClueText":"Digging, so to speak","ClueSource":2}],"MERCHANTBANKS":[{"ClueText":"British financial institutions","ClueSource":2}],"HICS":[{"ClueText":"Some juice boxes","ClueSource":2}],"NEB":[{"ClueText":"State north of Kan.","ClueSource":2}],"RIM":[{"ClueText":"Backboard attachment","ClueSource":2}],"EKED":[{"ClueText":"Barely made, with \"out\"","ClueSource":2}],"DEBATE":[{"ClueText":"Campaign face-off","ClueSource":2}],"MEDICINECABINET":[{"ClueText":"Vial venue","ClueSource":2}],"MADAM":[{"ClueText":"Polite address for a woman","ClueSource":2}],"EXOCET":[{"ClueText":"Anti-ship missile used in the Falklands War","ClueSource":2}],"DOLLARMENU":[{"ClueText":"List of cheap fast food","ClueSource":2}],"NAIAD":[{"ClueText":"Water nymph","ClueSource":2}],"ENDUP":[{"ClueText":"Eventually become","ClueSource":2}],"CELLO":[{"ClueText":"Low member of a string quartet","ClueSource":2}],"AWE":[{"ClueText":"Blow away","ClueSource":2}],"TAPES":[{"ClueText":"Cassettes, e.g.","ClueSource":2}],"AXONS":[{"ClueText":"Neural transmitters","ClueSource":2}],"ANEW":[{"ClueText":"From square one","ClueSource":2}],"TBA":[{"ClueText":"Undecided, on a TV schedule","ClueSource":2}],"DOLE":[{"ClueText":"Pineapple brand","ClueSource":2}],"SIDLE":[{"ClueText":"Move like a crab","ClueSource":2}],"SSN":[{"ClueText":"Common ID","ClueSource":2}],"ASAP":[{"ClueText":"\"Right away!\"","ClueSource":2}],"AUTOMATE":[{"ClueText":"Mechanize","ClueSource":2}],"ACL":[{"ClueText":"Initials for a knee part","ClueSource":2}],"SAUL":[{"ClueText":"\"Better Call ___\"","ClueSource":2}],"BUTTE":[{"ClueText":"Montana city whose name is a landform","ClueSource":2}],"BARN":[{"ClueText":"Building near a silo","ClueSource":2}],"MEATANDPOTATOES":[{"ClueText":"Basic ingredients","ClueSource":2}],"TEEMS":[{"ClueText":"Abounds","ClueSource":2}],"AYN":[{"ClueText":"\"The Fountainhead\" author Rand","ClueSource":2}],"TOOKTO":[{"ClueText":"Grew fond of","ClueSource":2}],"TREY":[{"ClueText":"Deuce topper","ClueSource":2}],"ORO":[{"ClueText":"Acapulco gold","ClueSource":2}],"MENWALKONMOON":[{"ClueText":"7/21/69 New York Times headline","ClueSource":2}],"WEBS":[{"ClueText":"Entanglements","ClueSource":2}],"ABET":[{"ClueText":"Help with a burglary","ClueSource":2}],"LOGE":[{"ClueText":"Balcony section","ClueSource":2}],"KOAN":[{"ClueText":"Zen paradox","ClueSource":2}],"OCHO":[{"ClueText":"Cuatro + cuatro","ClueSource":2}],"OMAN":[{"ClueText":"United Arab Emirates neighbor","ClueSource":2}],"NETS":[{"ClueText":"Circus safety devices","ClueSource":2}],"AHEM":[{"ClueText":"\"Beg pardon ...\"","ClueSource":2}],"APE":[{"ClueText":"Gibbon or orangutan","ClueSource":2}],"HAM":[{"ClueText":"Stage hog","ClueSource":2}],"EBOOK":[{"ClueText":"Kindle download","ClueSource":2}],"ACME":[{"ClueText":"Top spot?","ClueSource":2}],"PANS":[{"ClueText":"Vessels for frying bacon","ClueSource":2}],"BEGAT":[{"ClueText":"Sired, biblically","ClueSource":2}],"THAT":[{"ClueText":"Not this","ClueSource":2}],"EMU":[{"ClueText":"Australian runner","ClueSource":2}],"STENO":[{"ClueText":"Court reporter, briefly","ClueSource":2}],"EONS":[{"ClueText":"Long, long times","ClueSource":2}]}