{"SCARAB":[{"ClueText":"Beetle in ancient Egyptian art","ClueSource":2}],"SUR":[{"ClueText":"Central California's Big ___","ClueSource":2}],"CPU":[{"ClueText":"Technological brain, for short","ClueSource":2}],"ALB":[{"ClueText":"Balkan nation: Abbr.","ClueSource":2}],"RABBI":[{"ClueText":"One reading from the Torah","ClueSource":2}],"ATEIT":[{"ClueText":"Absorbed a loss","ClueSource":2}],"BERLE":[{"ClueText":"Milton of early TV","ClueSource":2}],"AWW":[{"ClueText":"\"That's adorable!\"","ClueSource":2}],"ALAI":[{"ClueText":"Jai ___","ClueSource":2}],"WINNIPEG":[{"ClueText":"Capital of Manitoba","ClueSource":2}],"WEDGE":[{"ClueText":"Common doorstop shape","ClueSource":2}],"SHAD":[{"ClueText":"Fish that produces roe","ClueSource":2}],"SWAY":[{"ClueText":"Clout","ClueSource":2}],"HONCHO":[{"ClueText":"Big kahuna","ClueSource":2}],"AVALON":[{"ClueText":"Where Excalibur was forged","ClueSource":2}],"DELETE":[{"ClueText":"Erase, as a file","ClueSource":2}],"UPLATE":[{"ClueText":"Awake in the wee hours, say","ClueSource":2}],"LIE":[{"ClueText":"Let sleeping dogs ___","ClueSource":2}],"WOVE":[{"ClueText":"Used a loom","ClueSource":2}],"RUBBERBAND":[{"ClueText":"The Beatles, in 1965?","ClueSource":2}],"BLAM":[{"ClueText":"Tire-popping sound","ClueSource":2}],"ANAL":[{"ClueText":"Nitpicky","ClueSource":2}],"BILLINGCYCLE":[{"ClueText":"Invoicing a trendy workout company?","ClueSource":2}],"CDTRAY":[{"ClueText":"Ejectable PC part","ClueSource":2}],"CHAITEA":[{"ClueText":"Spiced Indian drink","ClueSource":2}],"CHO":[{"ClueText":"Comedian Margaret","ClueSource":2}],"HIM":[{"ClueText":"That stag or ram","ClueSource":2}],"ACER":[{"ClueText":"Taiwanese computer giant","ClueSource":2}],"IED":[{"ClueText":"Iraq War weapon: Abbr.","ClueSource":2}],"HOT":[{"ClueText":"Scorching","ClueSource":2}],"HIC":[{"ClueText":"Juice box brand","ClueSource":2}],"MAP":[{"ClueText":"Diagram in many fantasy books","ClueSource":2}],"APNEA":[{"ClueText":"Nighttime breathlessness","ClueSource":2}],"TBONE":[{"ClueText":"Letter-shaped steak","ClueSource":2}],"BLTS":[{"ClueText":"Club cousins, at delis","ClueSource":2}],"OMEGAS":[{"ClueText":"Final Greek letters","ClueSource":2}],"GURU":[{"ClueText":"Zen master, e.g.","ClueSource":2}],"ANORAK":[{"ClueText":"Extra-warm coat","ClueSource":2}],"SNL":[{"ClueText":"Kate McKinnon's NBC show, briefly","ClueSource":2}],"PEARL":[{"ClueText":"June birthstone","ClueSource":2}],"AMS":[{"ClueText":"Early hrs.","ClueSource":2}],"RUNNINGMATE":[{"ClueText":"Barack Obama in 2008 or 2012, to Michelle?","ClueSource":2}],"ILLINOIS":[{"ClueText":"Lincoln's state?","ClueSource":2}],"ETCH":[{"ClueText":"Make art with acid","ClueSource":2}],"ROLLE":[{"ClueText":"Esther of \"Driving Miss Daisy\"","ClueSource":2}],"SYSTEM":[{"ClueText":"The \"S\" in GPS","ClueSource":2}],"EPA":[{"ClueText":"Green org.","ClueSource":2}],"MRI":[{"ClueText":"3D med. scan","ClueSource":2}],"AMOUR":[{"ClueText":"Love, in Nice","ClueSource":2}],"ASPICS":[{"ClueText":"Savory jellies","ClueSource":2}],"MUUMUU":[{"ClueText":"Flowing Hawaiian garment","ClueSource":2}],"ONMARS":[{"ClueText":"Where future humans may live","ClueSource":2}],"LAO":[{"ClueText":"Vientiane native","ClueSource":2}],"OPAL":[{"ClueText":"October birthstone","ClueSource":2}],"CPR":[{"ClueText":"Pre-ambulance procedure, briefly","ClueSource":2}],"SUN":[{"ClueText":"Bask","ClueSource":2}],"ALI":[{"ClueText":"Oscar winner Mahershala","ClueSource":2}],"LISZT":[{"ClueText":"Hungarian composer Franz","ClueSource":2}],"PADTHAI":[{"ClueText":"Fish sauce dish","ClueSource":2}],"ATSEA":[{"ClueText":"Away from port","ClueSource":2}],"DCELL":[{"ClueText":"Boom box battery","ClueSource":2}],"THANK":[{"ClueText":"Show gratefulness","ClueSource":2}],"PUMPKINPATCH":[{"ClueText":"Small square below an artsy jack-o'-lantern's smile?","ClueSource":2}],"PCBS":[{"ClueText":"Coolants once in wide use","ClueSource":2}],"PUPA":[{"ClueText":"Cocoon-bound bug","ClueSource":2}],"IMAC":[{"ClueText":"Jobs rollout of 1998","ClueSource":2}],"SOULSEARCH":[{"ClueText":"Existential quest that 17-, 20-, 38- and 58-Across may inspire?","ClueSource":2}],"RIA":[{"ClueText":"Coastal inlet (AIR anagram)","ClueSource":2}],"CNN":[{"ClueText":"\"Erin Burnett OutFront\" channel","ClueSource":2}],"HOE":[{"ClueText":"Loosen, as earth","ClueSource":2}],"CURB":[{"ClueText":"\"___ Your Enthusiasm\"","ClueSource":2}],"ZIP":[{"ClueText":"Close, as a suitcase","ClueSource":2}],"ELNINO":[{"ClueText":"Wacky weather source","ClueSource":2}],"SUSS":[{"ClueText":"Figure (out)","ClueSource":2}],"TSA":[{"ClueText":"Org. that X-rays shoes","ClueSource":2}],"ALKANE":[{"ClueText":"Fuel compound","ClueSource":2}]}